{
  "results": [
    {
      "object": "block",
      "id": "269ec12a-acd9-8057-8a4d-d1bf0e7920b7",
      "parent": {
        "type": "page_id",
        "page_id": "209ec12a-acd9-80f9-9ce3-f3ebe309bd57"
      },
      "created_time": "2025-09-09T03:45:00.000Z",
      "last_edited_time": "2025-09-12T07:44:00.000Z",
      "created_by": {
        "object": "user",
        "id": "02ad76c7-c57f-4001-a41c-fef09a1b9b83"
      },
      "last_edited_by": {
        "object": "user",
        "id": "02ad76c7-c57f-4001-a41c-fef09a1b9b83"
      },
      "has_children": false,
      "archived": false,
      "in_trash": false,
      "type": "heading_1",
      "heading_1": {
        "rich_text": [
          {
            "type": "text",
            "text": {
              "content": "关于域名利用CloudFlare进行CDN分发加速国内访问GitHub Page的问题",
              "link": null
            },
            "annotations": {
              "bold": false,
              "italic": false,
              "strikethrough": false,
              "underline": false,
              "code": false,
              "color": "default"
            },
            "plain_text": "关于域名利用CloudFlare进行CDN分发加速国内访问GitHub Page的问题",
            "href": null
          }
        ],
        "is_toggleable": false,
        "color": "default"
      }
    },
    {
      "object": "block",
      "id": "26bec12a-acd9-80c0-a4fc-e8a2f962adf7",
      "parent": {
        "type": "page_id",
        "page_id": "209ec12a-acd9-80f9-9ce3-f3ebe309bd57"
      },
      "created_time": "2025-09-11T12:54:00.000Z",
      "last_edited_time": "2025-09-11T12:55:00.000Z",
      "created_by": {
        "object": "user",
        "id": "02ad76c7-c57f-4001-a41c-fef09a1b9b83"
      },
      "last_edited_by": {
        "object": "user",
        "id": "02ad76c7-c57f-4001-a41c-fef09a1b9b83"
      },
      "has_children": false,
      "archived": false,
      "in_trash": false,
      "type": "image",
      "image": {
        "caption": [],
        "type": "file",
        "file": {
          "url": "https://prod-files-secure.s3.us-west-2.amazonaws.com/4f37e2c8-cb33-427c-85df-7f85e80016e8/65b5d223-add5-4acc-8e2c-451c21f729ea/image.png?X-Amz-Algorithm=AWS4-HMAC-SHA256&X-Amz-Content-Sha256=UNSIGNED-PAYLOAD&X-Amz-Credential=ASIAZI2LB466USX4GQMO%2F20260131%2Fus-west-2%2Fs3%2Faws4_request&X-Amz-Date=20260131T131333Z&X-Amz-Expires=3600&X-Amz-Security-Token=IQoJb3JpZ2luX2VjEO3%2F%2F%2F%2F%2F%2F%2F%2F%2F%2FwEaCXVzLXdlc3QtMiJGMEQCIExOtkbH12nHrLGnV6n62MIVYgDeEU1gghJXmLXrB8xOAiAUaLGFZQCze3uOR3Y0kGOORDTA1gHwea%2FeU8XBnsHyzyqIBAi1%2F%2F%2F%2F%2F%2F%2F%2F%2F%2F8BEAAaDDYzNzQyMzE4MzgwNSIMjw5AA6XCeS7Qi91JKtwD%2F%2BIEcOM1h3cVatTJZEaideVcCg6tabgTC%2BJ5S8Ht%2F4TddsBiezOdUJo74lTcLs5V8VnLiGAks7omUl473sZ73rY14tgJmPLjzyn7XpczVMfukjvW%2BKarAOsrEZ6bQq0jZ9JmN6PCV0Rr%2BgIwOPqf1BXZCniSM7z0yYx04cHLamv%2BjOZ5O%2F0wwEE24%2BFe6UzOf87YnRGGCaVZZ8v%2F95kc2Ja8IpsUD9i%2F0Ym2kkdZx3RWkon0v17FVnZdg%2BM0rW7%2BdUlfhXyGDozYo9222tyBkmxZ2lidB33SKW4I0YuSXa28V%2BMkGsFv%2BxppKxs9zZV7VSKySRXF2Tft3v8VzTKbNb6FRgEoqDETiHzzL24aJ%2Fi%2BRxZxlVBvxvIJzjxpSm0I4ZI7PQyzqQpx1pC9jfTaCTVZKxfw7sGMksyS6%2Fdngy6K%2FiDqceQmXcB2DeE%2BxeWnE2qv7g5D17k74eMj5fdwz4gCCYZGP9gnQAecjH9S2NUjFZYq2%2BOAxAXRfwkSX3FBiYTf5nhluXUcNE7O1w3FxfjnqW48xOOx5%2FE9ueTLFfxgOrm86VsFPqrl5ynNt6zreecr5f7JFopDZmjlLPS%2Fktmw4WYnnOh0v0oeIg65guayWqCr3y31KtSK0gIwg%2Bj3ywY6pgFZxpzqtpAYBrFTmnnHW406%2FoKoWRPiP8U28xWdvQTaqoibA%2ByD1CnJMqQ2K9AEskmXwf6y7ulBVHTinsNwBnpir%2FUAAwX810%2F1dFZstnDjkN2SSLgEVRbJY3QBRTKh%2Brxmbi2PCEr%2FHTb6L4kQQTp9BJIihLkHpQONtalS8YtOEeB5omT4tnD21qol5LFrXvFNhbu%2FSRM2ZIX95qYVMmaqUMOHO9NR&X-Amz-Signature=0b0788f205f63cac6ac66ee7cc4c28f9af7928b578677f0dac11b8ee728359ac&X-Amz-SignedHeaders=host&x-amz-checksum-mode=ENABLED&x-id=GetObject",
          "expiry_time": "2026-01-31T14:13:33.066Z"
        }
      }
    },
    {
      "object": "block",
      "id": "26cec12a-acd9-80ca-8929-f82363c650b4",
      "parent": {
        "type": "page_id",
        "page_id": "209ec12a-acd9-80f9-9ce3-f3ebe309bd57"
      },
      "created_time": "2025-09-12T07:43:00.000Z",
      "last_edited_time": "2025-11-12T18:02:00.000Z",
      "created_by": {
        "object": "user",
        "id": "02ad76c7-c57f-4001-a41c-fef09a1b9b83"
      },
      "last_edited_by": {
        "object": "user",
        "id": "02ad76c7-c57f-4001-a41c-fef09a1b9b83"
      },
      "has_children": false,
      "archived": false,
      "in_trash": false,
      "type": "heading_1",
      "heading_1": {
        "rich_text": [
          {
            "type": "text",
            "text": {
              "content": "关于利用Github Action在Ubuntu中进行构建并且部署到GitHub Page",
              "link": null
            },
            "annotations": {
              "bold": false,
              "italic": false,
              "strikethrough": false,
              "underline": false,
              "code": false,
              "color": "default"
            },
            "plain_text": "关于利用Github Action在Ubuntu中进行构建并且部署到GitHub Page",
            "href": null
          }
        ],
        "is_toggleable": false,
        "color": "default"
      }
    },
    {
      "object": "block",
      "id": "26cec12a-acd9-8044-8f78-dd22b6710657",
      "parent": {
        "type": "page_id",
        "page_id": "209ec12a-acd9-80f9-9ce3-f3ebe309bd57"
      },
      "created_time": "2025-09-12T07:44:00.000Z",
      "last_edited_time": "2025-09-12T07:44:00.000Z",
      "created_by": {
        "object": "user",
        "id": "02ad76c7-c57f-4001-a41c-fef09a1b9b83"
      },
      "last_edited_by": {
        "object": "user",
        "id": "02ad76c7-c57f-4001-a41c-fef09a1b9b83"
      },
      "has_children": false,
      "archived": false,
      "in_trash": false,
      "type": "paragraph",
      "paragraph": {
        "rich_text": [],
        "color": "default"
      }
    }
  ]
}